surveycodex/__init__.py
surveycodex/__main__.py
surveycodex/filter.py
surveycodex/helpers.py
surveycodex/rich.py
surveycodex/survey.py
surveycodex/utilities.py
surveycodex/data/CFHTLS.yaml
surveycodex/data/COSMOS.yaml
surveycodex/data/DES.yaml
surveycodex/data/Euclid_VIS.yaml
surveycodex/data/HSC.yaml
surveycodex/data/LSST.yaml
surveycodex-1.2.0.dist-info/LICENSE
surveycodex-1.2.0.dist-info/METADATA
surveycodex-1.2.0.dist-info/WHEEL
surveycodex-1.2.0.dist-info/entry_points.txt
surveycodex-1.2.0.dist-info/top_level.txt
surveycodex-1.2.0.dist-info/RECORD
