Metadata-Version: 2.1
Name: surveycodex
Version: 1.2.0
Summary: Tiny library of galaxy surveys most useful parameters with units
Home-page: https://github.com/LSSTDESC/surveycodex
Author: Alexandre Boucaud
Author-email: aboucaud@apc.in2p3.fr
License: MIT
Project-URL: Bug Tracker, https://github.com/LSSTDESC/surveycodex/issues
Platform: any
Classifier: Intended Audience :: Science/Research
Classifier: License :: OSI Approved :: MIT License
Classifier: Programming Language :: Python :: 3.7
Classifier: Programming Language :: Python :: 3.8
Classifier: Programming Language :: Python :: 3.9
Classifier: Programming Language :: Python :: 3.10
Classifier: Programming Language :: Python :: 3.11
Classifier: Programming Language :: Python :: 3.12
Classifier: Topic :: Scientific/Engineering :: Astronomy
Classifier: Development Status :: 3 - Alpha
Requires-Python: >=3.7
License-File: LICENSE
Requires-Dist: astropy >=4.3
Requires-Dist: pyyaml >=5.1
Provides-Extra: dev
Requires-Dist: pre-commit >=2.17 ; extra == 'dev'
Requires-Dist: pytest >=6.0 ; extra == 'dev'
Requires-Dist: pytest-cov >=3.0 ; extra == 'dev'
Requires-Dist: pytest-astropy-header >=0.2 ; extra == 'dev'
Requires-Dist: rich >=13.7 ; extra == 'dev'
Provides-Extra: docs
Requires-Dist: mkdocs >=1.2 ; extra == 'docs'
Requires-Dist: mkdocs-material >=8.2 ; extra == 'docs'
Requires-Dist: mkdocstrings >=0.18 ; extra == 'docs'
Requires-Dist: mkdocstrings-python >=1.9 ; extra == 'docs'
Requires-Dist: pytkdocs[numpy-style] >=0.16 ; extra == 'docs'
Provides-Extra: scripts
Requires-Dist: speclite >=0.15 ; extra == 'scripts'
